mllm/__init__.py
mllm/config.py
mllm/db/conn.py
mllm/db/models.py
mllm/env.py
mllm/img.py
mllm/models.py
mllm/prompt.py
mllm/router.py
mllm/util.py
mllm-0.1.57.dist-info/LICENSE
mllm-0.1.57.dist-info/METADATA
mllm-0.1.57.dist-info/WHEEL
mllm-0.1.57.dist-info/RECORD
