Metadata-Version: 2.1
Name: mllm
Version: 0.1.57
Summary: Multimodal Large Language Models
License: Apache 2.0
Author: Patrick Barker
Author-email: patrickbarkerco@gmail.com
Requires-Python: >=3.10,<4.0
Classifier: License :: Other/Proprietary License
Classifier: Programming Language :: Python :: 3
Classifier: Programming Language :: Python :: 3.10
Classifier: Programming Language :: Python :: 3.11
Classifier: Programming Language :: Python :: 3.12
Provides-Extra: gemini
Requires-Dist: google-generativeai (>=0.6.0,<0.7.0) ; extra == "gemini"
Requires-Dist: litellm (>=1.61.13,<2.0.0)
Requires-Dist: numpy (==1.26.4)
Requires-Dist: tenacity (>=8.2.3,<9.0.0)
Requires-Dist: threadmem (>=0.2.39,<0.3.0)
